{"bangCanDoiKeToan":{"Nam":{"values":["q1 2020","q4 2019","q3 2019","q2 2019","q1 2019"]},"tai san":{"values":["","","","",""]},"a: tai san ngan han":{"values":["478,919","649,512","606,868","683,860","595,236"]},"i. tien va tuong duong tien":{"values":["54,029","73,804","32,728","113,190","16,061"]},"1. tien":{"values":["12,429","14,304","16,728","7,660","12,761"]},"2. cac khoan tuong duong tien":{"values":["41,600","59,500","16,000","105,530","3,300"]},"ii. gia tri thuan dau tu ngan han":{"values":["28,239","207,000","226,544","213,126","213,126"]},"1. dau tu ngan han":{"values":["28,239","207,000","207,000","209,682","209,682"]},"2. du phong dau tu ngan han":{"values":["","","","",""]},"iii. cac khoan phai thu":{"values":["254,721","222,850","239,531","244,266","241,895"]},"1. phai thu khach hang":{"values":["338,599","305,165","323,920","333,834","371,827"]},"2. tra truoc nguoi ban":{"values":["13,267","6,501","6,525","6,213","5,406"]},"3. phai thu noi bo":{"values":["","","","",""]},"4. phai thu ve xdcb":{"values":["","","","",""]},"5. phai thu khac":{"values":["49,786","58,116","53,195","48,329","8,771"]},"6. du phong no kho doi":{"values":["-146,932","-146,932","-144,109","-144,109","-144,109"]},"iv. hang ton kho, rong":{"values":["141,303","144,783","107,047","111,827","120,460"]},"1. hang ton kho":{"values":["141,365","144,845","107,109","111,889","120,522"]},"2. du phong giam gia htk":{"values":["-62","-62","-62","-62","-62"]},"v. tai san luu dong khac":{"values":["626","1,074","1,019","1,451","3,695"]},"1. tra truoc ngan":{"values":["321","280","376","464","2,784"]},"2. thue vat phai thu":{"values":["110","","34","420",""]},"3. phai thu thue khac":{"values":["195","794","609","567","911"]},"4. tai san luu dong khac":{"values":["","","","",""]},"b. tai san dai han":{"values":["412,316","409,954","425,838","414,135","441,553"]},"i. phai thu dai han":{"values":["","","","","6,741"]},"1. phai thu khach hang dai han":{"values":["","","","","6,741"]},"2. phai thu noi bo dai han":{"values":["","","","",""]},"3. phai thu dai han khac":{"values":["","","","",""]},"4. du phong phai thu dai han":{"values":["","","","",""]},"ii. tai san co dinh":{"values":["103,240","105,689","108,374","112,580","116,529"]},"1. gtcl tscd huu hinh":{"values":["102,692","105,086","107,713","111,864","115,756"]},"nguyen gia tscd huu hinh":{"values":["280,940","279,962","279,577","295,987","295,918"]},"khau hao luy ke tscd huu hinh":{"values":["-178,248","-174,877","-171,863","-184,123","-180,162"]},"2. gtcl tai san thue tai chinh":{"values":["","","","",""]},"nguyen gia tai san thue tai chinh":{"values":["","","","",""]},"khau hao luy ke tai san thue tai chinh":{"values":["","","","",""]},"3. gtcl tai san co dinh vo hinh":{"values":["547","604","660","717","773"]},"nguyen gia tscd vo hinh":{"values":["3,052","3,052","3,052","3,052","3,052"]},"khau hao luy ke tscd vo hinh":{"values":["-2,505","-2,449","-2,392","-2,336","-2,279"]},"4. xay dung co ban do dang":{"values":["","","","",""]},"iii. gia tri rong tai san dau tu":{"values":["","","","",""]},"1. nguyen gia tai san dau tu":{"values":["","2,374","2,374","2,374","2,374"]},"2. khau hao luy ke tai san dau tu":{"values":["","-2,374","-2,374","-2,374","-2,374"]},"iv. dau tu dai han":{"values":["284,150","278,777","291,399","276,018","293,120"]},"1. dau tu vao cac cong ty con":{"values":["","","","",""]},"2. dau tu vao cac cong ty lien ket":{"values":["284,150","278,777","291,399","276,018","293,120"]},"3. dau tu dai han khac":{"values":["","","","",""]},"4. du phong giam gia dau tu dai han":{"values":["","","","",""]},"v. tai san dai han khac":{"values":["23,755","24,478","25,697","24,541","24,849"]},"1. tra truoc dai han":{"values":["5,467","5,560","5,517","4,361","4,038"]},"2. thue thu nhap hoan lai phai thu":{"values":["","","","",""]},"3. tai san dai han khac":{"values":["","","","",""]},"vi. loi the thuong mai":{"values":["","","","",""]},"tong cong tai san":{"values":["891,235","1,059,466","1,032,706","1,097,995","1,036,790"]},"nguon von":{"values":["","","","",""]},"a. no phai tra":{"values":["267,882","389,673","378,723","413,684","372,090"]},"i. no ngan han":{"values":["265,244","385,609","374,770","409,494","365,728"]},"1. vay ngan han":{"values":["117,820","305,566","301,875","305,247","296,092"]},"2. phai tra nha cung cap ngan han":{"values":["70,317","52,222","47,297","72,808","47,644"]},"3. tam ung cua khach hang":{"values":["2,285","3,813","2,020","4,511","3,205"]},"4. cac khoan phai tra ve thue":{"values":["5,185","369","6,785","815","2,621"]},"5. phai tra nguoi lao dong":{"values":["2,814","9,179","6,948","5,054","4,012"]},"6. chi phi phai tra":{"values":["670","7,495","1,933","6,980","1,164"]},"7. phai tra noi bo":{"values":["","","","",""]},"8. phai tra ve xay dung co ban":{"values":["","","","",""]},"9. phai tra khac":{"values":["61,189","2,702","3,378","3,565","3,145"]},"10. du phong cac khoan phai tra ngan han":{"values":["3,957","2,772","2,849","2,502","526"]},"ii. no dai han":{"values":["2,637","4,065","3,953","4,190","6,362"]},"1. phai tra nha cung cap dai han":{"values":["","","","",""]},"2. phai tra noi bo dai han":{"values":["","","","",""]},"3. phai tra dai han khac":{"values":["483","503","383","50","50"]},"4. vay dai han":{"values":["","","","",""]},"5. thue thu nhap hoan lai phai tra":{"values":["","","","",""]},"6. du phong tro cap thoi viec":{"values":["","","","",""]},"7. du phong cac khoan cong no dai han":{"values":["2,154","3,561","3,570","4,140","6,312"]},"b. von chu so huu":{"values":["623,353","669,793","653,983","684,310","664,699"]},"i. von va cac quy":{"values":["617,933","664,146","648,108","678,207","658,368"]},"1. von gop":{"values":["387,047","387,047","387,047","387,047","368,000"]},"2. thang du von co phan":{"values":["11,771","11,771","11,771","11,771","153"]},"3. von khac":{"values":["","","","",""]},"4. co phieu quy":{"values":["-1,589","-1,589","-1,589","-1,589","-1,589"]},"5. chenh lech danh gia lai tai san":{"values":["","","","",""]},"6. chenh lech ty gia":{"values":["","","","",""]},"7. quy dau tu va phat trien":{"values":["7,926","7,926","7,926","7,926","7,926"]},"8. quy du phong tai chinh":{"values":["","","","",""]},"9. quy khac":{"values":["4,509","4,509","4,509","4,509","4,509"]},"10. lai chua phan phoi":{"values":["208,069","254,282","238,243","268,343","236,079"]},"ii. von ngan sach nha nuoc va quy khac":{"values":["5,420","5,647","5,875","6,103","6,331"]},"1. quy khen thuong, phuc loi":{"values":["","","","",""]},"2. von ngan sach nha nuoc":{"values":["","","","",""]},"c. loi ich co dong thieu so":{"values":["","","","",""]},"tong cong nguon von":{"values":["891,235","1,059,466","1,032,706","1,097,995","1,036,790"]}},"baoCaoKetQuaKd":{"Nam":{"values":["q1 2020","q4 2019","q3 2019","q2 2019","q1 2019"]},"1. doanh so":{"values":["128,792","139,668","115,197","148,703","98,359"]},"2. cac khoan giam tru":{"values":["-72","-76","-108","-116","-43"]},"3. doanh so thuan":{"values":["128,721","139,592","115,090","148,587","98,316"]},"4. gia von hang ban":{"values":["-107,272","-121,063","-88,427","-125,174","-73,685"]},"5. lai gop":{"values":["21,448","18,529","26,663","23,414","24,631"]},"6. thu nhap tai chinh":{"values":["5,649","38,497","10,483","39,790","640"]},"7. chi phi tai chinh":{"values":["-6,326","-6,888","-7,729","-7,761","-2,542"]},"- trong do: chi phi lai vay":{"values":["-1,731","-1,317","3,294","-7,655","-2,164"]},"8. chi phi ban hang":{"values":["-5,198","-7,858","-5,368","-5,910","-5,258"]},"9. chi phi quan ly doanh nghiep":{"values":["-7,284","-12,304","-8,604","-11,322","-13,347"]},"10. lai/ tu hoat dong kinh doanh":{"values":["13,664","17,354","30,826","21,110","21,321"]},"11. thu nhap khac":{"values":["59","329","141","405","1"]},"12. chi phi khac":{"values":["-149","-626","-10","-37","-13"]},"13. thu nhap khac, rong":{"values":["-89","-297","131","369","-12"]},"13b. lai/ tu cong ty lien doanh":{"values":["","","","",""]},"14. lai/ rong truoc thue":{"values":["13,575","17,057","30,957","21,478","21,309"]},"15. thue thu nhap doanh nghiep – hien thoi":{"values":["-1,964","-1,019","-3,233","-640","-937"]},"16. thue thu nhap doanh nghiep – hoan lai":{"values":["","","","-300",""]},"17. chi phi thue thu nhap doanh nghiep":{"values":["-1,964","-1,019","-3,233","-940","-937"]},"18. lai/ thuan sau thue":{"values":["11,611","16,038","27,724","20,539","20,372"]},"19. loi ich co dong thieu so":{"values":["0","-1","0","9","33"]},"20. co dong cua cong ty me":{"values":["11,611","16,038","27,724","20,530","20,339"]},"21. lai co ban tren co phieu":{"values":["263.00","422.00","733.00","535.00","555.00"]},"22. lai tren co phieu pha loang":{"values":["263","422","","535",""]}},"luuChuyenTienTegiantiep":{"Nam":{"values":["q1 2020","q4 2019","q3 2019","q2 2019","q1 2019"]},"i. luu chuyen tien tu hoat dong kinh doanh":{"values":["","","","",""]},"1. lai truoc thue":{"values":["13,575","17,057","30,957","21,478","21,309"]},"2. khau hao tscd":{"values":["4,439","5,136","5,203","3,146","4,391"]},"3. chi phi du phong":{"values":["223","2,909","1,438","-197","-411"]},"4. lai/ chenh lech ty gia chua thuc hien":{"values":["","-48","-4","5",""]},"5. lai/ tu thanh ly tai san co dinh":{"values":["","","","",""]},"6. lai/ tu hoat dong dau tu":{"values":["-5,708","-43,979","-5,439","-22,903","-17,619"]},"7. chi phi lai vay":{"values":["5,816","17,196","-3,290","7,655","2,164"]},"8. thu lai va co tuc":{"values":["","","","",""]},"9. lai/ truoc nhung thay doi von co dinh":{"values":["18,344","-1,729","28,866","9,185","9,834"]},"10. /giam cac khoan phai thu":{"values":["-31,870","11,034","-36,708","45,813","32,091"]},"11. /giam hang ton kho":{"values":["3,480","-37,737","23,498","8,633","-10,681"]},"12.  cac khoan phai tra":{"values":["7,840","-8,546","-22,906","24,915","-32,068"]},"13. /giam chi phi tra truoc":{"values":["52","54","-1,068","1,997","-1,843"]},"14. chi phi lai vay da tra":{"values":["-6,326","-7,980","-13,063","-1,849","-2,029"]},"15. thue tndn da nop":{"values":["-1,163","-4,350","850","-1,161","-3,922"]},"16. tien thu khac tu cac hoat dong kinh doanh":{"values":["1,514","375","377","2,053","34"]},"17. tien chi khac cho hoat dong kinh doanh":{"values":["-1,721","-461","-2,549","-1,038","-482"]},"luu chuyen tien te rong tu cac hoat dong san xuat kinh doanh":{"values":["168,911","-49,339","-20,023","88,548","-203,748"]},"ii. luu chuyen tu hoat dong dau tu":{"values":["","","","",""]},"1. tien mua tai san co dinh va cac tai san dai han khac":{"values":["-2,085","-463","-1,059","-713","-342"]},"2. tien thu tu thanh ly, nhuong ban tscd":{"values":["59","381","214","-36","36"]},"3. tien cho vay hoac mua cong cu no":{"values":["","","","",""]},"4. tien thu tu cho vay hoac thu tu phat hanh cong cu no":{"values":["","16,100","","",""]},"5. dau tu vao cac doanh nghiep khac":{"values":["","","","",""]},"6. tien thu tu viec ban cac khoan dau tu vao cac doanh nghiep khac":{"values":["","","","",""]},"7. co tuc va tien lai nhan duoc":{"values":["1,214","70,649","12,328","180","408"]},"luu chuyen tien te rong tu hoat dong dau tu":{"values":["-813","86,667","11,482","-570","102"]},"iii. luu chuyen tien tu hoat dong tai chinh":{"values":["","","","",""]},"1. tien thu tu phat hanh co phieu va von gop":{"values":["","","","",""]},"2. chi tra cho viec mua lai, tra lai co phieu":{"values":["","","","",""]},"3. tien thu duoc cac khoan di vay":{"values":["56,949","75,278","83,264","73,245","268,984"]},"4. tien tra cac khoan di vay":{"values":["-244,822","-71,711","-97,362","-64,090","-91,228"]},"5. tien thanh toan von goc di thue tai chinh":{"values":["","","","",""]},"6. co tuc da tra":{"values":["","128","-57,824","",""]},"7. tien lai da nhan":{"values":["","","","",""]},"luu chuyen tien te tu hoat dong tai chinh":{"values":["-187,873","3,695","-71,921","9,156","177,756"]},"luu chuyen tien thuan trong ky":{"values":["-19,775","41,023","-80,462","97,133","-25,890"]},"tien va cac khoan tuong duong tien dau ky":{"values":["73,804","32,728","113,190","16,061","41,951"]},"anh huong cua chenh lech ty gia":{"values":["","52","","-5",""]},"tien va cac khoan tuong duong tien cuoi ky":{"values":["54,029","73,804","32,728","113,190","16,061"]}},"thuyetMinhBCTC":{"Nam":{"values":["q1 2020","q4 2019","q3 2019","q2 2019","q1 2019"]},"i. tien":{"values":["54,029","73,804","32,728","113,190","16,061"]},"tien mat":{"values":["734","319","844","97","820"]},"tien gui ngan hang":{"values":["11,695","13,985","15,885","7,563","11,941"]},"tien dang chuyen":{"values":["","","","",""]},"tien va tuong duong tien":{"values":["41,600","59,500","16,000","105,530","3,300"]},"ii. dau tu ngan han":{"values":["28,239","207,000","226,544","213,126","213,126"]},"chung khoan dau tu ngan han":{"values":["28,239","207,000","207,000","209,682","209,682"]},"dau tu ngan han khac":{"values":["","","","",""]},"du phong giam gia dtnh":{"values":["","","","","","","","","",""]},"iii. phai thu ngan han khac":{"values":["49,786","58,116","53,195","48,329","8,771"]},"phai thu ve co phan hoa":{"values":["","","","",""]},"phai thu ve co tuc va loi nhuan duoc chia":{"values":["","","","",""]},"phai thu nguoi lao dong":{"values":["","","","",""]},"phai thu khac":{"values":["49,786","58,116","53,195","48,329","8,771"]},"iv. hang ton kho":{"values":["141,365","144,845","107,109","111,889","120,522"]},"hang mua dang di duong":{"values":["","","","",""]},"nguyen lieu, vat lieu":{"values":["58,975","63,015","40,980","40,799","47,624","48,954","68,697","35,488","30,299","32,089"]},"cong cu, dung cu":{"values":["1,166","1,057","698","758","928"]},"chi phi sx, kd do dang":{"values":["40,723","40,707","32,791","34,779","27,294"]},"thanh pham":{"values":["32,612","21,986","25,147","27,612","37,120"]},"hang hoa":{"values":["7,889","18,080","7,493","7,940","7,556"]},"hang gui di ban":{"values":["","","","",""]},"hang hoa kho bao thue":{"values":["","","","",""]},"hang hoa bat dong san":{"values":["","","","",""]},"v. tai san luu dong khac":{"values":["","","","",""]},"tam ung":{"values":["","","","",""]},"tai san thieu cho xu ly":{"values":["","","","",""]},"cam co, ky quy, ky cuoc nh":{"values":["","","","",""]},"khac":{"values":["","","","","","670","7,495","1,933","6,980","1,164","60,177","2,336","2,396","2,373","3,145"]},"vi. phai thu dai han khac":{"values":["","","","",""]},"ky quy, ky cuoc dai han":{"values":["","","","",""]},"cac khoan tien nhan uy thac":{"values":["","","","","","","","","",""]},"phai thu dai han khac":{"values":["","","","",""]},"vii. nguyen gia":{"values":["280,940","279,962","279,577","295,987","295,918"]},"nguyen gia dau ky":{"values":["279,962","295,710","295,710","295,710","295,710","174,877","176,398","176,398","176,398","176,398","","","","","","","","","","","3,052","3,052","3,052","3,052","3,052","2,449","2,223","2,223","2,223","2,223"]},"tang trong ky":{"values":["1,841","11,956","10,462","467","398","3,983","16,035","11,986","7,880","3,919","","","","","","","","","","","","","","","","56","226","169","113","56"]},"giam trong ky":{"values":["-864","-27,704","-26,595","-190","-190","-612","-17,556","-16,521","-155","-155","","","","","","","","","","","","","","","","","","","",""]},"viii. hao mon tscdhh":{"values":["178,248","174,877","171,863","184,123","180,162"]},"ix. nguyen gia tscd ttc":{"values":["","","","",""]},"x. hao mon tscd ttc":{"values":["","","","",""]},"xi. nguyen gia tscdvh":{"values":["3,052","3,052","3,052","3,052","3,052"]},"xii. hao mon tscdvh":{"values":["2,505","2,449","2,392","2,336","2,279"]},"xiii. dau tu dai han khac":{"values":["","","","",""]},"dau tu co phieu":{"values":["","","","",""]},"dau tu trai phieu":{"values":["","","","",""]},"dau tu tin phieu, ky phieu":{"values":["","","","",""]},"cho vay dai han":{"values":["","","","",""]},"dau tu dai han khac":{"values":["","","","",""]},"xiv. vay va no nh":{"values":["117,820","305,566","301,875","305,247","296,092"]},"cho vay ngan han":{"values":["117,820","305,566","301,875","305,247","296,092"]},"vay dai han den han tra":{"values":["","","","",""]},"xv. cac khoan phai tra ve thue":{"values":["5,185","369","6,785","815","2,621"]},"thue gtgt":{"values":["1,702","72","1,585","60","1,241"]},"thue ttdb":{"values":["","","","","","","","","",""]},"thue xnk":{"values":["","","","",""]},"thue tndn":{"values":["1,052","251","3,582","708","932"]},"thue tncn":{"values":["38","46","29","46","448"]},"thue tai nguyen":{"values":["","","","",""]},"thue nha dat va tien thue dat":{"values":["2,393","","1,589","",""]},"cac loai thue khac":{"values":["","","","",""]},"cac khoan phi, le phi khac":{"values":["","","","",""]},"xvi. chi phi phai tra":{"values":["670","7,495","1,933","6,980","1,164"]},"trich truoc cf luong nghi phep":{"values":["","","","",""]},"chi phi scl tscd":{"values":["","","","",""]},"chi phi trongthoi gian ngung kd":{"values":["","","","",""]},"xvii. phai tra phai nop khac":{"values":["61,189","2,702","3,378","3,565","3,145"]},"tai san thua cho xl":{"values":["","","","",""]},"kinh phi cong doan":{"values":["1,013","366","983","",""]},"bh xh":{"values":["","","","1,192",""]},"bh yt":{"values":["","","","",""]},"phai tra ve cph":{"values":["","","","",""]},"nhan ky quy, ky cuoc nh":{"values":["","","","",""]},"doanh thu chua thuc hien":{"values":["","","","",""]},"xviii. vay dai han":{"values":["","","","",""]},"vay ngan hang":{"values":["","","","",""]},"vay doi tuong khac":{"values":["","","","",""]},"trai phieu phat hanh":{"values":["","","","",""]},"thue tai chinh":{"values":["","","","",""]},"no dai han khac":{"values":["","","","",""]},"xix. von chu so huu":{"values":["","","","","368,000"]},"von gop cua nha nuoc":{"values":["","","","",""]},"von dau tu cua doi tuong khac":{"values":["","","","","368,000"]},"xx. doanh thu":{"values":["128,792","139,668","115,197","148,703","98,359"]},"giam tru doanh thu":{"values":["104,509","105,731","77,453","123,552","71,541"]},"doanh thu cung cap dich vu":{"values":["24,283","33,937","37,744","25,151","26,818"]},"doanh thu hop dong xay dung":{"values":["","","","",""]},"xxi. giam tru doanh thu":{"values":["72","76","108","116","43"]},"chiet khau thuong mai":{"values":["","","","",""]},"reductions in prices of goods sold":{"values":["","","","",""]},"sales returns":{"values":["72","76","108","116","43"]},"vat payable":{"values":["","","","",""]},"thue xuat khau":{"values":["","","","",""]},"xxi. gia von hang ban":{"values":["107,272","121,063","88,427","125,174","73,685"]},"gia von hang hoa da ban":{"values":["59,954","59,339","26,649","68,310","26,188"]},"gia von thanh pham da ban":{"values":["31,490","41,638","35,108","41,985","33,550"]},"gia von cua dich vu cung cap":{"values":["15,828","20,085","26,669","14,879","13,947"]},"gia tri con lai, chi phi nhuong ban, thanh ly bds dau tu da ban":{"values":["","","","",""]},"chi phi kinh doanh bds dau tu":{"values":["","","","",""]},"hao hut, mat mat hang ton kho":{"values":["","","","",""]},"cac khoan chi phi vuot muc binh thuong":{"values":["","","","",""]},"xxii. thu nhap tai chinh":{"values":["5,649","38,497","10,483","39,790","640"]},"lai tien gui, tien cho vay":{"values":["1,214","6,249","5,549","7,458","421"]},"lai dau tu trai phieu, ky phieu, tin phieu":{"values":["","","","",""]},"co tuc, loi nhuan duoc chia":{"values":["","32,200","-347","32,547",""]},"lai ban ngoai te":{"values":["","","","",""]},"lai chenh lech ty gia da thuc hien":{"values":["","48","2","0","4"]},"lai chenh lech ty gia chua thuc hien":{"values":["","","","",""]},"lai ban hang tra cham":{"values":["","","","",""]},"doanh thu hoat dong tai chinh khac":{"values":["","","5,279","-215","215"]},"xxiii. chi phi tai chinh":{"values":["6,326","6,888","7,729","7,761","2,542"]},"lai tien vay":{"values":["1,731","1,317","-3,294","7,655","2,164"]},"chiet khau thanh toan, lai ban hang tra cham":{"values":["315","153","303","122","38"]},"lo do thanh ly cac khoan dau tu ngan han, dai han":{"values":["","","","",""]},"lo ban ngoai te":{"values":["","","","",""]},"lo chenh lech ty gia da thuc hien":{"values":["","","","7","0"]},"lo chenh lech ty gia chua thuc hien":{"values":["","","","",""]},"du phong giam gia cac khoan dau tu ngan han, dai han":{"values":["","","","",""]},"chi phi tai chinh khac":{"values":["4,280","5,418","10,721","-23","340"]},"xxiv. chi phi san xuat theo yeu to":{"values":["77,715","102,962","68,269","67,807","69,247"]},"chi phi nhan cong":{"values":["13,791","16,865","16,417","19,654","18,183"]},"chi phi khau hao tai san co dinh":{"values":["3,809","3,875","3,942","3,777","3,760"]},"chi phi dich vu mua ngoai":{"values":["5,228","5,112","11,968","5,384","4,278"]},"chi phi khac bang tien":{"values":["5,933","8,412","454","8,693","10,937"]}},"chitieutaichinh":{"don vi khoi luong 1cp - don vi gia x1000 ":{"values":["q1 2020","q4 2019","q3 2019","q2 2019","q1 2019",""]},"i. chi so co phieu":{"values":["","","","","",""]},"so cp luu hanh binh quan":{"values":["38,575,472.47","38,094,019.50","37,607,275.87","37,120,532.23","37,279,253.32",""]},"so cp luu hanh binh quan pha loang":{"values":["38,575,472.47","38,094,019.50","37,607,275.87","37,120,532.23","37,279,253.32",""]},"gia tri so sach/mot co phieu ":{"values":["16,170.40","17,305.23","16,891.55","17,675.10","16,886.10",""]},"doanh so/mot co phieu ":{"values":["13,800.35","13,011.62","15,010.02","15,036.84","12,823.00",""]},"gia tri so sach huu hinh/mot co phieu ":{"values":["16,156.20","17,289.63","16,879.70","17,661.79","18,041.48",""]},"gia tri dong tien tao ra/mot co phieu ":{"values":["4,378.71","-5,893.26","-1,424.05","-920.60","-2,200.81",""]},"lai co ban tren co phieu":{"values":["1,967.67","2,221.65","3,574.30","3,833.65","3,459.64",""]},"lai tren co phieu pha loang":{"values":["1,967.67","2,221.65","3,574.30","3,833.65","3,459.64",""]},"eps truoc thu nhap khac":{"values":["1,965.46","2,217.89","3,546.72","3,802.09","3,403.24",""]},"eps co ban theo bctc nam":{"values":["2,226.00","2,226.00","2,498.00","2,498.00","2,498.00",""]},"he so beta":{"values":["0.07","-0.44","2.74","0.69","-0.14",""]},"ii. suc khoe tai chinh":{"values":["","","","","",""]},"ty suat thanh toan tien mat":{"values":["0.31","0.73","0.64","0.79","0.62",""]},"ty suat thanh toan nhanh":{"values":["1.27","1.31","1.33","1.40","1.30",""]},"ty suat thanh toan hien thoi":{"values":["1.81","1.68","1.62","1.67","1.63",""]},"von vay dai han/von csh":{"values":["","","","","",""]},"von vay dai han/tong tai san":{"values":["","","","","",""]},"von vay ngan han/von csh":{"values":["0.19","0.46","0.46","0.45","0.45",""]},"von vay ngan han/tong tai san":{"values":["0.13","0.29","0.29","0.28","0.29",""]},"cong no ngan han/von csh":{"values":["0.43","0.58","0.57","0.60","0.55",""]},"cong no ngan han/tong tai san":{"values":["0.30","0.36","0.36","0.37","0.35",""]},"tong cong no/von csh":{"values":["0.43","0.58","0.58","0.60","0.56",""]},"tong cong no/tong tai san":{"values":["0.30","0.37","0.37","0.38","0.36",""]},"iii. hieu qua hoat dong":{"values":["","","","",""]},"roe %":{"values":["11.54","12.88","20.31","22.19","21.34",""]},"roce %":{"values":["13.68","17.29","6.65","8.34","9.12",""]},"roa %":{"values":["7.44","8.75","13.30","15.01","14.82",""]},"he so quay vong phai thu khach hang":{"values":["1.63","1.40","1.59","1.71","1.67",""]},"thoi gian trung binh thu tien khach hang ":{"values":["223.24","259.84","230.18","213.41","218.24",""]},"he so quay vong htk":{"values":["3.50","3.21","4.14","4.01","3.29",""]},"thoi gian trung binh xu ly htk ":{"values":["104.31","113.82","88.08","91.08","111.10",""]},"he so quay vong phai tra nha cung cap":{"values":["7.29","6.59","7.77","7.28","6.88",""]},"thoi gian trung binh thanh toan cho nha cung cap ":{"values":["50.10","55.43","46.96","50.12","53.09",""]},"doanh so tinh tren dau nguoi":{"values":["2,136,506,500.54","2,014,397,939.49","2,323,781,339.55","2,327,933,450.40","1,985,197,319.83",""]},"loi nhuan thuan tinh tren dau nguoi":{"values":["304,866,791.72","340,050,928.72","550,499,696.54","582,176,994.55","528,585,444.52",""]},"iv. chi so co tuc":{"values":["","","","",""]},"ty suat co tuc %":{"values":["","10.79","","","",""]},"he so thanh toan co tuc %":{"values":["","148.11","","","",""]},"he so chi tra co tuc %":{"values":["","67.52","","","",""]},"v. chi so loi nhuan va chat luong loi nhuan":{"values":["","","","",""]},"ty suat loi nhuan gop %":{"values":["16.93","18.59","19.55","21.09","23.09",""]},"ty suat ebitda %":{"values":["17.01","25.89","10.36","11.54","13.77",""]},"ty suat ebit %":{"values":["17.01","22.83","7.67","9.31","11.27",""]},"ty suat loi nhuan truoc thue %":{"values":["15.61","18.10","24.80","26.56","27.95",""]},"ty suat loi nhuan thuan %":{"values":["14.27","16.88","23.69","25.01","26.63",""]},"ty le doanh so/von hoa ":{"values":["0.94","0.94","1.00","1.06","0.92",""]},"he so vong quay tai san ":{"values":["0.52","0.52","0.57","0.61","0.57",""]},"he so vong quay von csh ":{"values":["0.81","0.76","0.87","0.90","0.82",""]},"ty suat thue tndn thuc te ":{"values":["-1.35","-1.22","-1.11","-1.56","-1.32",""]},"chat luong loi nhuan theo bctc ":{"values":["3,674.45","","3,981.89","-1,939.42","-2,211.17",""]},"chat luong loi nhuan theo lctt ":{"values":["4,342.24","","1,828.53","-2,803.08","-3,148.18",""]},"vi. chi so dinh gia":{"values":["","","","",""]},"p/e co ban":{"values":["7.49","6.26","4.20","3.71","4.05",""]},"p/e pha loang":{"values":["7.49","6.26","4.20","3.71","4.05",""]},"p/e truoc thu nhap khac":{"values":["7.49","6.27","4.23","3.74","4.11",""]},"he so gia co phieu/tri gia so sach ":{"values":["0.91","0.80","0.89","0.81","0.83",""]},"he so gia co phieu/doanh so tren co phieu ":{"values":["1.07","1.07","1.00","0.95","1.09",""]},"he so gia/tri gia so sach tshh ":{"values":["0.91","0.80","0.89","0.81","0.78",""]},"he so gia/dong tien ":{"values":["3.36","-2.36","-10.53","-15.46","-6.36",""]},"gia tri doanh nghiep/doanh so":{"values":["1.19","1.53","1.46","1.28","1.75",""]},"gia tri doanh nghiep/ebitda":{"values":["6.98","5.91","14.14","11.07","12.68",""]},"gia tri doanh nghiep/ebit":{"values":["6.98","6.70","19.11","13.72","15.49",""]},"vii. toc do tang truong":{"values":["","","","",""]},"toc do tang truong doanh so thuan %":{"values":["-7.79","-7.60","-22.54","51.13","-54.62",""]},"toc do tang truong lai gop %":{"values":["15.75","-17.45","13.88","-4.94","-35.87",""]},"toc do tang truong ebitda %":{"values":["","5.31","","","",""]},"toc do tang truong ebit %":{"values":["","3.38","","","",""]},"toc do tang truong lai truoc thue %":{"values":["-20.41","-11.03","44.13","0.79","-69.46",""]},"toc do tang truong lai thuan %":{"values":["-27.60","-10.05","34.99","0.82","-70.23",""]},"toc do tang truong eps %":{"values":["-10.01","-10.67","-2.79","9.39","-3.73",""]},"toc do tang truong tong tai san %":{"values":["-15.88","21.13","-5.95","5.90","18.53",""]},"toc do tang truong von csh %":{"values":["-6.93","3.92","-4.43","2.95","3.13",""]},"toc do tang truong von dieu le %":{"values":["","5.18","","5.18","",""]}},"luuChuyenTienTe":{"Nam":{"values":["q1 2015","q4 2014","q3 2014","q2 2014","q1 2014"]},"i. luu chuyen tien tu hoat dong kinh doanh":{"values":["","","","",""]},"1. tien thu tu ban hang, cung cap dich vu va dt khac":{"values":["113,967","156,709","134,997","150,193","92,894"]},"2. tien chi tra cho nguoi cung cap hh va dich vu":{"values":["-78,457","-123,350","-117,802","-132,000","-78,539"]},"3. tien chi tra cho nguoi lao dong":{"values":["-16,886","-11,790","-10,641","-10,743","-17,646"]},"4. tien chi tra lai vay":{"values":["-254","-290","-233","-212","-345"]},"5. tien da nop thue thu nhap doanh nghiep":{"values":["-1,730","-898","-1,699","-949","-2,183"]},"6. tien thu khac tu hoat dong kinh doanh":{"values":["3,337","7,019","1,915","-1,315","4,328"]},"7. tien chi khac cho hoat dong kinh doanh":{"values":["-12,054","-15,467","-6,862","-2,225","-11,463"]},"8. khau hao tscd":{"values":["","","","",""]},"luu chuyen tien te rong tu cac hoat dong san xuat kinh doanh":{"values":["7,923","11,933","-324","2,750","-12,955"]},"ii. luu chuyen tu hoat dong dau tu":{"values":["","","","",""]},"1. tien mua tai san co dinh va cac tai san dai han khac":{"values":["-134","-1,119","-7,596","-140","-611"]},"2. tien thu tu thanh ly, nhuong ban tscd":{"values":["","36","40","47",""]},"3. tien cho vay hoac mua cong cu no":{"values":["-5,900","-61,945","-21,600","-41,983","-36,945"]},"4.":{"values":["25,500","52,642","19,203","21,848","22,875"]},"5. dau tu vao cac doanh nghiep khac":{"values":["","","","",""]},"6. tien thu tu viec ban cac khoan dau tu vao cac doanh nghiep khac":{"values":["","","","",""]},"7. co tuc va tien lai nhan duoc":{"values":["1,014","1,407","813","5,414","59,891"]},"luu chuyen tien te rong tu hoat dong dau tu":{"values":["20,479","-8,979","-9,140","-14,814","45,209"]},"iii. luu chuyen tien tu hoat dong tai chinh":{"values":["","","","",""]},"1. tien thu tu phat hanh co phieu va von gop":{"values":["","","","",""]},"2. chi tra cho viec mua lai, tra lai co phieu":{"values":["","","","",""]},"3. tien thu duoc cac khoan di vay":{"values":["4,378","7,729","6,954","10,047","4,616"]},"4. tien tra cac khoan di vay":{"values":["-4,365","-9,781","-7,815","-6,778","-8,609"]},"5. tien thanh toan von goc di thue tai chinh":{"values":["","","","",""]},"6. co tuc da tra":{"values":["-7","-10","-32","-42,304","-2,580"]},"7. tien lai da nhan":{"values":["","","","",""]},"luu chuyen tien te tu hoat dong tai chinh":{"values":["6","-2,062","-893","-39,036","-6,572"]},"luu chuyen tien thuan trong ky":{"values":["28,408","892","-10,357","-51,100","25,682"]},"tien va cac khoan tuong duong tien dau ky":{"values":["18,096","17,203","25,602","78,661","52,979"]},"anh huong cua chenh lech ty gia":{"values":["","0","","",""]},"tien va cac khoan tuong duong tien cuoi ky":{"values":["46,504","18,096","15,245","27,560","78,661"]}}}